{"7": {"nombre": "Ossand\u00f3n Ossand\u00f3n", "region": "Regi\u00f3n Metropolitana de Santiago", "partido": "Renovaci\u00f3n Nacional", "mail": "mjossandon@senado.cl"}, "6": {"nombre": "Pugh Pugh", "region": "Regi\u00f3n de Valpara\u00edso", "partido": "Independiente", "mail": "kpugh@senado.cl"}, "11": {"nombre": "Quintana Quintana", "region": "Regi\u00f3n de la Araucan\u00eda", "partido": "Partido Por la Democracia", "mail": "jquintana@senado.cl"}, "3": {"nombre": "Guillier Guillier", "region": "Regi\u00f3n de Antofagasta", "partido": "Independiente", "mail": "aguillier@senado.cl"}, "15": {"nombre": "Goic Goic", "region": "Regi\u00f3n de Magallanes y la Ant\u00e1rtica Chilena\n\n", "partido": "Partido Dem\u00f3crata Cristiano", "mail": "cgoic@senado.cl"}, "9": {"nombre": "Rinc\u00f3n Rinc\u00f3n", "region": "Regi\u00f3n del Maule", "partido": "Partido Dem\u00f3crata Cristiano", "mail": "xrincon@senado.cl"}, "12": {"nombre": "Von Baer Von Baer", "region": "Regi\u00f3n de Los R\u00edos", "partido": "Uni\u00f3n Dem\u00f3crata Independiente", "mail": "evonbaer@senado.cl"}, "1": {"nombre": "Insulza Insulza", "region": "Regi\u00f3n de Arica y Parinacota", "partido": "Partido Socialista", "mail": "jminsulza@senado.cl"}, "2": {"nombre": "Soria Soria", "region": "Regi\u00f3n de Tarapac\u00e1\n\n", "partido": "Partido Por la Democracia", "mail": "jsoria@senado.cl"}, "8": {"nombre": "Letelier Letelier", "region": "Regi\u00f3n del Libertador General Bernardo O'Higgins", "partido": "Partido Socialista", "mail": "jpletelier@senado.cl"}, "10": {"nombre": "Van Rysselberghe Van Rysselberghe", "region": "Regi\u00f3n del B\u00edo-B\u00edo", "partido": "Uni\u00f3n Dem\u00f3crata Independiente", "mail": "jvanr@senado.cl"}, "13": {"nombre": "Quinteros Quinteros", "region": "Regi\u00f3n de Los Lagos", "partido": "Partido Socialista", "mail": "rquinteros@senado.cl"}, "5": {"nombre": "Pizarro Pizarro", "region": "Regi\u00f3n de Coquimbo\n\n", "partido": "Partido Dem\u00f3crata Cristiano", "mail": "jpizarro@senado.cl"}, "14": {"nombre": "Sandoval Sandoval", "region": "Regi\u00f3n de Ays\u00e9n del General Carlos Ib\u00e1\u00f1ez del Campo ", "partido": "Uni\u00f3n Dem\u00f3crata Independiente", "mail": "dsandoval@senado.cl"}, "4": {"nombre": "Provoste Provoste", "region": "Regi\u00f3n de Atacama", "partido": "Partido Dem\u00f3crata Cristiano", "mail": "yasnaprovoste@senado.cl"}}